biomesh/__init__.py
biomesh/adapt.py
biomesh/fe.py
biomesh/filter.py
biomesh/laplace.py
biomesh/merge.py
biomesh/mesh.py
biomesh/reorder.py
biomesh/run_gmsh.py
biomesh/utils.py
biomesh-0.6.0.dist-info/METADATA
biomesh-0.6.0.dist-info/WHEEL
biomesh-0.6.0.dist-info/licenses/LICENSE
biomesh-0.6.0.dist-info/RECORD
