Metadata-Version: 2.4
Name: biomesh
Version: 0.6.0
Summary: Create meshes from segmented imaging data for finite element simulations using Gmsh.
Project-URL: Homepage, https://github.com/TUM-LNM/biomesh
Project-URL: Bug Tracker, https://github.com/TUM-LNM/biomesh/issues
Author: The biomesh Authors
License: The MIT License (MIT)
License-File: LICENSE
Classifier: Development Status :: 3 - Alpha
Classifier: Intended Audience :: Developers
Classifier: License :: OSI Approved :: MIT License
Classifier: Operating System :: OS Independent
Classifier: Programming Language :: Python :: 3
Classifier: Programming Language :: Python :: 3.10
Classifier: Programming Language :: Python :: 3.11
Classifier: Programming Language :: Python :: 3.12
Requires-Python: >=3.10
Requires-Dist: lnmmeshio>=5.6.4
Requires-Dist: loguru>=0.7.2
Requires-Dist: meshio<6,>=5.3.5
Requires-Dist: numpy>=1.26.4
Requires-Dist: python-utils>=2.3.0
Requires-Dist: pyyaml<7,>=6.0.0
Requires-Dist: scipy
Requires-Dist: symfem==2025.6.0
Requires-Dist: tqdm==4.66.5
